Metadata-Version: 2.1
Name: odoo14-addon-l10n-es-facturae
Version: 14.0.2.7.1
Summary: Creación de Facturae
Home-page: https://github.com/OCA/l10n-spain
Author: ASR-OSS, FactorLibre, Tecon, Comunitea, Tecnativa, Creu Blanca, Odoo Community Association (OCA)
Author-email: support@odoo-community.org
License: AGPL-3
Platform: UNKNOWN
Classifier: Programming Language :: Python
Classifier: Framework :: Odoo
Classifier: Framework :: Odoo :: 14.0
Classifier: License :: OSI Approved :: GNU Affero General Public License v3
Requires-Python: >=3.6
Requires-Dist: cryptography <39
Requires-Dist: odoo14-addon-account-payment-partner
Requires-Dist: odoo14-addon-base-iso3166
Requires-Dist: odoo14-addon-l10n-es-aeat
Requires-Dist: odoo14-addon-l10n-es-partner
Requires-Dist: odoo14-addon-report-qweb-parameter
Requires-Dist: odoo14-addon-report-xml
Requires-Dist: odoo <14.1dev,>=14.0a
Requires-Dist: pyOpenSSL
Requires-Dist: pycountry
Requires-Dist: xmlsig
